florestbotfunctions/__init__.py
florestbotfunctions-1.9.0.dist-info/METADATA
florestbotfunctions-1.9.0.dist-info/WHEEL
florestbotfunctions-1.9.0.dist-info/top_level.txt
florestbotfunctions-1.9.0.dist-info/RECORD
