Metadata-Version: 2.1
Name: florestbotfunctions
Version: 1.9.0
Summary: Функции бота Флореста в одной библиотеке.
Author: florestdev
Author-email: florestone4185@internet.ru
Project-URL: Social Resources, https://taplink.cc/florestone4185
Project-URL: My bot, https://t.me/postbotflorestbot
Project-URL: GitHub of Project, https://github.com/florestdev/florestbotfunctions
Requires-Python: >=3.10
Requires-Dist: g4f
Requires-Dist: curl-cffi
Requires-Dist: pytubefix
Requires-Dist: pillow
Requires-Dist: qrcode
Requires-Dist: gtts
Requires-Dist: google-api-python-client
Requires-Dist: faker
Requires-Dist: bs4
Requires-Dist: SpeechRecognition
Requires-Dist: pygame
Requires-Dist: colorama
Requires-Dist: pyinstaller
Requires-Dist: MukeshAPI
Requires-Dist: vkpymusic
Requires-Dist: httpx
Requires-Dist: vk-api
Requires-Dist: aiohttp
Requires-Dist: aiosmtplib
Requires-Dist: aiofiles
Requires-Dist: selenium
Requires-Dist: webdriver-manager
Requires-Dist: tqdm
Requires-Dist: aio-mc-rcon
Requires-Dist: mcrcon
Requires-Dist: numpy
Requires-Dist: yoloface
Requires-Dist: IPython
Requires-Dist: telethon
Requires-Dist: pandas
Requires-Dist: openpyxl
Requires-Dist: xlsxwriter
Requires-Dist: mcstatus
Requires-Dist: aiohttp-socks
Requires-Dist: phub==4.7
Requires-Dist: fake-useragent
Requires-Dist: deepface
Requires-Dist: tensorflow
Requires-Dist: yt-dlp
Requires-Dist: torch
Requires-Dist: openai-whisper
Requires-Dist: librosa
Requires-Dist: moviepy
Requires-Dist: feedparser
Requires-Dist: newspaper3k
Requires-Dist: DonationAlertsAPI==2.0.2
Requires-Dist: duckduckgo-search
